Metadata-Version: 2.1
Name: stylish-vk-api
Version: 0.0.2
Summary: Emulation of user actions in Vk
Home-page: 
Author: Vadim
Author-email: fancybear@internet.ru
License: MIT
Keywords: vk
Classifier: Development Status :: 5 - Production/Stable
Classifier: Intended Audience :: Education
Classifier: Operating System :: POSIX :: Linux
Classifier: License :: OSI Approved :: MIT License
Classifier: Programming Language :: Python :: 3
License-File: LICENSE.txt
